pya2l/__init__.py
pya2l/a2l_listener.py
pya2l/a2llg.g4
pya2l/a2lparser.py
pya2l/a2lparser_ext.cp310-win_amd64.pyd
pya2l/a2lparser_ext.cp311-win_amd64.pyd
pya2l/a2lparser_wrapper.cpp
pya2l/aml/__init__.py
pya2l/aml/aml_lexer.hpp
pya2l/aml/aml_parser.hpp
pya2l/aml/aml_visitor.cpp
pya2l/aml/aml_visitor.h
pya2l/aml/classes.py
pya2l/aml/db.py
pya2l/aml/ifdata_lexer.py
pya2l/aml/ifdata_parser.py
pya2l/aml/klasses.hpp
pya2l/aml/listener.py
pya2l/aml/marshal.cpp
pya2l/aml/parser.cpp
pya2l/aml/parser.hpp
pya2l/aml/types.hpp
pya2l/aml/unmarshal.cpp
pya2l/aml/unmarshal.hpp
pya2l/aml.g4
pya2l/aml_parser.cpp
pya2l/amlparser_wrapper.cpp
pya2l/api/__init__.py
pya2l/api/create.py
pya2l/api/inspect.py
pya2l/api/validate.py
pya2l/build/__init__.py
pya2l/build/README.rst
pya2l/buildGrammar.bat
pya2l/buildGrammars.cmd
pya2l/cgen/__init__.py
pya2l/cgen/templates/__init__.py
pya2l/cgen/templates/a2l.tmpl
pya2l/classes.py
pya2l/cse_units.py
pya2l/examples/ASAP2_Demo_V161.a2l
pya2l/examples/etas.aml
pya2l/examples/ex01.py
pya2l/examples/ex02.py
pya2l/examples/ex03.py
pya2l/examples/ex04.py
pya2l/examples/ex_variants.py
pya2l/examples/ifdata_tester.py
pya2l/examples/parse_aml_tst.py
pya2l/examples/variants.a2l
pya2l/examples/vector.aml
pya2l/exceptions.py
pya2l/extensions/a2l.tokens
pya2l/extensions/a2lparser.hpp
pya2l/extensions/a2ltoken.hpp
pya2l/extensions/asam_types.hpp
pya2l/extensions/cmake/.FindANTLR.cmake.swp
pya2l/extensions/cmake/antlr4-generator.cmake.in
pya2l/extensions/cmake/antlr4-runtime.cmake.in
pya2l/extensions/cmake/Antlr4Package.md
pya2l/extensions/cmake/ExternalAntlr4Cpp.cmake
pya2l/extensions/cmake/FindANTLR.cmake
pya2l/extensions/ctre.hpp
pya2l/extensions/exceptions.cpp
pya2l/extensions/exceptions.hpp
pya2l/extensions/FreeA2LParser/A2L.tmp
pya2l/extensions/FreeA2LParser/FreeA2LParser.sln
pya2l/extensions/FreeA2LParser/FreeA2LParser.vcxproj
pya2l/extensions/FreeA2LParser/FreeA2LParser.vcxproj.filters
pya2l/extensions/FreeA2LParser/FreeA2LParser.vcxproj.user
pya2ldb-1.0.319.dist-info/entry_points.txt
pya2ldb-1.0.319.dist-info/licenses/LICENSE
pya2ldb-1.0.319.dist-info/METADATA
pya2ldb-1.0.319.dist-info/WHEEL
pya2ldb-1.0.319.dist-info/RECORD
