Metadata-Version: 2.4
Name: pya2ldb
Version: 1.0.319
Summary: A2L for Python
License: GPLv2
License-File: LICENSE
Author: Christoph Schueler
Author-email: cpu12.gems@googlemail.com
Requires-Python: >=3.10,<4.0
Classifier: Development Status :: 4 - Beta
Classifier: Intended Audience :: Developers
Classifier: License :: OSI Approved :: GNU General Public License v2 (GPLv2)
Classifier: License :: Other/Proprietary License
Classifier: Programming Language :: Python :: 3
Classifier: Programming Language :: Python :: 3.10
Classifier: Programming Language :: Python :: 3.11
Classifier: Programming Language :: Python :: 3.12
Classifier: Programming Language :: Python :: 3.13
Classifier: Programming Language :: Python :: 3.14
Classifier: Programming Language :: Python :: 3.9
Classifier: Topic :: Scientific/Engineering
Classifier: Topic :: Software Development
Requires-Dist: Mako (>=1.3.5,<2.0.0)
Requires-Dist: SQLAlchemy (>=2.0.30,<3.0.0)
Requires-Dist: chardet (>=5.2.0,<6.0.0)
Requires-Dist: numexpr (>=2.14.1,<3.0.0)
Requires-Dist: numpy (>=1.26.4,<3)
Requires-Dist: rich (>=14.2,<15.0)
Requires-Dist: scipy (>=1.15.0,<2.0.0)
Project-URL: Homepage, https://github.com/christoph2/pyA2L
